univ360/__init__.py
univ360/univ360.py
univ360-0.1.7.dist-info/METADATA
univ360-0.1.7.dist-info/WHEEL
univ360-0.1.7.dist-info/top_level.txt
univ360-0.1.7.dist-info/RECORD
