Metadata-Version: 2.1
Name: univ360
Version: 0.1.7
Summary: Module for v360 files
Author: Anton Zhidkov, Vlad Bespalov
Classifier: Programming Language :: Python :: 3
Requires-Python: >=3.10
Requires-Dist: urllib3
Requires-Dist: Pillow
